tssim/__init__.py
tssim/examples.py
tssim/functions.py
tssim/series.py
tssim/tracks.py
tssim-0.1.1.dist-info/DESCRIPTION.rst
tssim-0.1.1.dist-info/METADATA
tssim-0.1.1.dist-info/RECORD
tssim-0.1.1.dist-info/WHEEL
tssim-0.1.1.dist-info/metadata.json
tssim-0.1.1.dist-info/top_level.txt
