Metadata-Version: 2.0
Name: tssim
Version: 0.1.1
Summary: .
Home-page: https://github.com/mansenfranzen/tssim
Author: Franz Woellert
Author-email: franz.woellert@gmail.com
License: MIT license
Keywords: tssim
Platform: UNKNOWN
Classifier: Development Status :: 2 - Pre-Alpha
Classifier: Intended Audience :: Developers
Classifier: License :: OSI Approved :: MIT License
Classifier: Natural Language :: English
Classifier: Programming Language :: Python :: 2
Classifier: Programming Language :: Python :: 2.6
Classifier: Programming Language :: Python :: 2.7
Classifier: Programming Language :: Python :: 3
Classifier: Programming Language :: Python :: 3.3
Classifier: Programming Language :: Python :: 3.4
Classifier: Programming Language :: Python :: 3.5
Requires-Dist: bokeh
Requires-Dist: numpy
Requires-Dist: pandas
